demo/RdfPrefix.py
demo/__init__.py
demo/main.py
demo/properties.py
pyfuseki/__init__.py
pyfuseki/config.py
pyfuseki/exceptions.py
pyfuseki/register.py
pyfuseki/term.py
pyfuseki/asyncFuseki/__init__.py
pyfuseki/asyncFuseki/async_fuseki.py
pyfuseki/asyncFuseki/fuseki_resp.py
pyfuseki/model/BindingItem.py
pyfuseki/model/__init__.py
pyfuseki/ontology_mapper/BaseProps.py
pyfuseki/ontology_mapper/BaseRdfPrefixEnum.py
pyfuseki/ontology_mapper/__init__.py
pyfuseki/ontology_mapper/global_namespace_manager.py
pyfuseki/ontology_mapper/prefixes.py
pyfuseki/rdf/__init__.py
pyfuseki/rdf/rdf_prefix.py
pyfuseki/rdf/rdf_property.py
pyfuseki/syncFuseki/__init__.py
pyfuseki/syncFuseki/fuseki.py
pyfuseki/utils/FusekiUtils.py
pyfuseki/utils/RdfUtils.py
pyfuseki/utils/__init__.py
tests/__init__.py
tests/insert_demo.py
tests/rdf_prefix_test.py
pyfuseki-1.6.dist-info/LICENSE
pyfuseki-1.6.dist-info/METADATA
pyfuseki-1.6.dist-info/WHEEL
pyfuseki-1.6.dist-info/top_level.txt
pyfuseki-1.6.dist-info/RECORD
