Metadata-Version: 2.1
Name: pyfuseki
Version: 1.6
Summary: An easy way to mix together OWL and Jena Fuseki.
Home-page: https://github.com/yubinCloud/pyfuseki
Author: Bin Yu
Author-email: yubin_SkyWalker@yeah.net
License: UNKNOWN
Platform: UNKNOWN
Classifier: Programming Language :: Python :: 3
Classifier: License :: OSI Approved :: Artistic License
Classifier: Operating System :: OS Independent
Requires-Python: >=3.6
Requires-Dist: httpx
Requires-Dist: rdflib
Requires-Dist: pydantic
Requires-Dist: SPARQLWrapper
